transpose.py
text_transpose-1.0.0.dist-info/LICENSE
text_transpose-1.0.0.dist-info/METADATA
text_transpose-1.0.0.dist-info/WHEEL
text_transpose-1.0.0.dist-info/entry_points.txt
text_transpose-1.0.0.dist-info/top_level.txt
text_transpose-1.0.0.dist-info/RECORD
