Metadata-Version: 2.1
Name: text-transpose
Version: 1.0.0
Summary: Transpose, flip, rotate textual data.
Home-page: https://github.com/nlitsme/transpose/
Author: Willem Hengeveld
Author-email: itsme@xs4all.nl
License: MIT
Keywords: transpose,row-column-data,rotate,filter
Platform: UNKNOWN
Classifier: Topic :: Text Processing :: Filters
Classifier: Environment :: Console
Classifier: Intended Audience :: End Users/Desktop
Classifier: Intended Audience :: Developers
Classifier: License :: OSI Approved :: MIT License
Classifier: Operating System :: OS Independent
Classifier: Programming Language :: Python :: 2
Classifier: Programming Language :: Python :: 3
Classifier: Topic :: Utilities
Requires-Python: >=2.7
